{
  "LSVM_A": 160,
  "LSVM_B": 4,
  "proximity": [
    {
      "rowPosition": 1,
      "columnPosition": 1,
      "id": 7,
      "worldId": 48
    },
    {
      "rowPosition": 1,
      "columnPosition": 2,
      "id": 8,
      "worldId": 48
    },
    {
      "rowPosition": 1,
      "columnPosition": 0,
      "id": 6,
      "worldId": 48
    },
    {
      "rowPosition": 0,
      "columnPosition": 3,
      "id": 3,
      "worldId": 48
    },
    {
      "rowPosition": 0,
      "columnPosition": 1,
      "id": 1,
      "worldId": 48
    },
    {
      "rowPosition": 0,
      "columnPosition": 2,
      "id": 2,
      "worldId": 48
    },
    {
      "rowPosition": 0,
      "columnPosition": 0,
      "id": 0,
      "worldId": 48
    },
    {
      "rowPosition": 2,
      "columnPosition": 1,
      "id": 13,
      "worldId": 48
    }
  ],
  "values": {
    "0": 9.528001255108083711320432485081255435943603515625,
    "1": 7.6005535766328140567793525406159460544586181640625,
    "2": 3.2628369989428591679825331084430217742919921875,
    "3": 15.6577897280069127106116866343654692173004150390625,
    "6": 12.896873925826337625721862423233687877655029296875,
    "7": 8.106708266484876190816066809929907321929931640625,
    "8": 10.846079775035516234993338002823293209075927734375,
    "13": 4.88210433679305833010175774688832461833953857421875
  },
  "setupType": "Regional Bidder Setup",
  "population": 0,
  "id": 2,
  "worldId": 48,
  "setup": {
    "valueInterval": {
      "minValue": 3.0,
      "maxValue": 20.0
    },
    "proximitySize": 2,
    "a": 160,
    "b": 4,
    "setupName": "Regional Bidder Setup",
    "numberOfBidders": 5
  },
  "implementation": "org.spectrumauctions.sats.core.model.lsvm.LSVMBidder"
}