{
  "LSVM_A": 320,
  "LSVM_B": 10,
  "proximity": [
    {
      "rowPosition": 0,
      "columnPosition": 0,
      "id": 0,
      "worldId": 96
    },
    {
      "rowPosition": 0,
      "columnPosition": 1,
      "id": 1,
      "worldId": 96
    },
    {
      "rowPosition": 0,
      "columnPosition": 2,
      "id": 2,
      "worldId": 96
    },
    {
      "rowPosition": 0,
      "columnPosition": 3,
      "id": 3,
      "worldId": 96
    },
    {
      "rowPosition": 0,
      "columnPosition": 4,
      "id": 4,
      "worldId": 96
    },
    {
      "rowPosition": 0,
      "columnPosition": 5,
      "id": 5,
      "worldId": 96
    },
    {
      "rowPosition": 1,
      "columnPosition": 0,
      "id": 6,
      "worldId": 96
    },
    {
      "rowPosition": 1,
      "columnPosition": 1,
      "id": 7,
      "worldId": 96
    },
    {
      "rowPosition": 1,
      "columnPosition": 2,
      "id": 8,
      "worldId": 96
    },
    {
      "rowPosition": 1,
      "columnPosition": 3,
      "id": 9,
      "worldId": 96
    },
    {
      "rowPosition": 1,
      "columnPosition": 4,
      "id": 10,
      "worldId": 96
    },
    {
      "rowPosition": 1,
      "columnPosition": 5,
      "id": 11,
      "worldId": 96
    },
    {
      "rowPosition": 2,
      "columnPosition": 0,
      "id": 12,
      "worldId": 96
    },
    {
      "rowPosition": 2,
      "columnPosition": 1,
      "id": 13,
      "worldId": 96
    },
    {
      "rowPosition": 2,
      "columnPosition": 2,
      "id": 14,
      "worldId": 96
    },
    {
      "rowPosition": 2,
      "columnPosition": 3,
      "id": 15,
      "worldId": 96
    },
    {
      "rowPosition": 2,
      "columnPosition": 4,
      "id": 16,
      "worldId": 96
    },
    {
      "rowPosition": 2,
      "columnPosition": 5,
      "id": 17,
      "worldId": 96
    }
  ],
  "values": {
    "0": 8.131754528107666857295043882913887500762939453125,
    "1": 8.3524639217235883137391283526085317134857177734375,
    "2": 5.3198739004331603297259789542295038700103759765625,
    "3": 4.0504453570740235335279066930525004863739013671875,
    "4": 6.63004399923813902972824507742188870906829833984375,
    "5": 8.5503663381570920165586358052678406238555908203125,
    "6": 5.1827555752209892858672901638783514499664306640625,
    "7": 6.856842368744306526195941842161118984222412109375,
    "8": 4.79948914740752652363653396605513989925384521484375,
    "9": 3.3850022497887675143601882155053317546844482421875,
    "10": 4.6806879265150360680536323343403637409210205078125,
    "11": 7.0762702791195639662191751995123922824859619140625,
    "12": 8.1887106880590199153857611236162483692169189453125,
    "13": 4.3453884924929724320463719777762889862060546875,
    "14": 8.447323166372530778289728914387524127960205078125,
    "15": 7.168014125642127254423030535690486431121826171875,
    "16": 7.136123111672642238545449799858033657073974609375,
    "17": 7.72542764738728937601308643934316933155059814453125
  },
  "setupType": "National Bidder Setup",
  "population": 0,
  "id": 0,
  "worldId": 96,
  "setup": {
    "valueInterval": {
      "minValue": 3.0,
      "maxValue": 9.0
    },
    "proximitySize": -1,
    "a": 320,
    "b": 10,
    "setupName": "National Bidder Setup",
    "numberOfBidders": 1
  },
  "implementation": "org.spectrumauctions.sats.core.model.lsvm.LSVMBidder"
}