{
  "LSVM_A": 160,
  "LSVM_B": 4,
  "proximity": [
    {
      "rowPosition": 1,
      "columnPosition": 3,
      "id": 9,
      "worldId": 67
    },
    {
      "rowPosition": 1,
      "columnPosition": 4,
      "id": 10,
      "worldId": 67
    },
    {
      "rowPosition": 1,
      "columnPosition": 1,
      "id": 7,
      "worldId": 67
    },
    {
      "rowPosition": 1,
      "columnPosition": 2,
      "id": 8,
      "worldId": 67
    },
    {
      "rowPosition": 1,
      "columnPosition": 0,
      "id": 6,
      "worldId": 67
    },
    {
      "rowPosition": 0,
      "columnPosition": 3,
      "id": 3,
      "worldId": 67
    },
    {
      "rowPosition": 0,
      "columnPosition": 1,
      "id": 1,
      "worldId": 67
    },
    {
      "rowPosition": 0,
      "columnPosition": 2,
      "id": 2,
      "worldId": 67
    },
    {
      "rowPosition": 2,
      "columnPosition": 3,
      "id": 15,
      "worldId": 67
    },
    {
      "rowPosition": 2,
      "columnPosition": 1,
      "id": 13,
      "worldId": 67
    },
    {
      "rowPosition": 2,
      "columnPosition": 2,
      "id": 14,
      "worldId": 67
    }
  ],
  "values": {
    "1": 3.527666574716715075510364840738475322723388671875,
    "2": 5.22181595806400888903908708016388118267059326171875,
    "3": 12.300151621170630988899574731476604938507080078125,
    "6": 14.05365018974833191123252618126571178436279296875,
    "7": 17.934361278938609984834329225122928619384765625,
    "8": 3.522979630276910523178912626462988555431365966796875,
    "9": 14.40061163009038835980391013436019420623779296875,
    "10": 5.6620123880464827692549079074524343013763427734375,
    "13": 19.044119020350184001699744840152561664581298828125,
    "14": 12.136869016425674061565587180666625499725341796875,
    "15": 14.1097663856270258975200704298913478851318359375
  },
  "setupType": "Regional Bidder Setup",
  "population": 0,
  "id": 5,
  "worldId": 67,
  "setup": {
    "valueInterval": {
      "minValue": 3.0,
      "maxValue": 20.0
    },
    "proximitySize": 2,
    "a": 160,
    "b": 4,
    "setupName": "Regional Bidder Setup",
    "numberOfBidders": 5
  },
  "implementation": "org.spectrumauctions.sats.core.model.lsvm.LSVMBidder"
}