{
  "LSVM_A": 320,
  "LSVM_B": 10,
  "proximity": [
    {
      "rowPosition": 0,
      "columnPosition": 0,
      "id": 0,
      "worldId": 10
    },
    {
      "rowPosition": 0,
      "columnPosition": 1,
      "id": 1,
      "worldId": 10
    },
    {
      "rowPosition": 0,
      "columnPosition": 2,
      "id": 2,
      "worldId": 10
    },
    {
      "rowPosition": 0,
      "columnPosition": 3,
      "id": 3,
      "worldId": 10
    },
    {
      "rowPosition": 0,
      "columnPosition": 4,
      "id": 4,
      "worldId": 10
    },
    {
      "rowPosition": 0,
      "columnPosition": 5,
      "id": 5,
      "worldId": 10
    },
    {
      "rowPosition": 1,
      "columnPosition": 0,
      "id": 6,
      "worldId": 10
    },
    {
      "rowPosition": 1,
      "columnPosition": 1,
      "id": 7,
      "worldId": 10
    },
    {
      "rowPosition": 1,
      "columnPosition": 2,
      "id": 8,
      "worldId": 10
    },
    {
      "rowPosition": 1,
      "columnPosition": 3,
      "id": 9,
      "worldId": 10
    },
    {
      "rowPosition": 1,
      "columnPosition": 4,
      "id": 10,
      "worldId": 10
    },
    {
      "rowPosition": 1,
      "columnPosition": 5,
      "id": 11,
      "worldId": 10
    },
    {
      "rowPosition": 2,
      "columnPosition": 0,
      "id": 12,
      "worldId": 10
    },
    {
      "rowPosition": 2,
      "columnPosition": 1,
      "id": 13,
      "worldId": 10
    },
    {
      "rowPosition": 2,
      "columnPosition": 2,
      "id": 14,
      "worldId": 10
    },
    {
      "rowPosition": 2,
      "columnPosition": 3,
      "id": 15,
      "worldId": 10
    },
    {
      "rowPosition": 2,
      "columnPosition": 4,
      "id": 16,
      "worldId": 10
    },
    {
      "rowPosition": 2,
      "columnPosition": 5,
      "id": 17,
      "worldId": 10
    }
  ],
  "values": {
    "0": 7.6939412763359040781097064609639346599578857421875,
    "1": 4.78391421548047279799220632412470877170562744140625,
    "2": 8.611549918772379186293619568459689617156982421875,
    "3": 5.124403864191403812355929403565824031829833984375,
    "4": 6.326265552280855075650833896361291408538818359375,
    "5": 8.90909710651903452571787056513130664825439453125,
    "6": 6.2438341039397204923488970962353050708770751953125,
    "7": 5.858811167868768876587637350894510746002197265625,
    "8": 6.756509023623539889058520202524960041046142578125,
    "9": 8.683524063056839992214008816517889499664306640625,
    "10": 7.880993212454729501814654213376343250274658203125,
    "11": 4.0295961853185389145437511615455150604248046875,
    "12": 4.96642412968734081601951402262784540653228759765625,
    "13": 7.40487367326541789935845372383482754230499267578125,
    "14": 6.27260738179960863902806522673927247524261474609375,
    "15": 7.62734528848973081238682425464503467082977294921875,
    "16": 8.62659277889539310990585363470017910003662109375,
    "17": 4.3707208201652605339404544793069362640380859375
  },
  "setupType": "National Bidder Setup",
  "population": 0,
  "id": 0,
  "worldId": 10,
  "setup": {
    "valueInterval": {
      "minValue": 3.0,
      "maxValue": 9.0
    },
    "proximitySize": -1,
    "a": 320,
    "b": 10,
    "setupName": "National Bidder Setup",
    "numberOfBidders": 1
  },
  "implementation": "org.spectrumauctions.sats.core.model.lsvm.LSVMBidder"
}