{
  "LSVM_A": 320,
  "LSVM_B": 10,
  "proximity": [
    {
      "rowPosition": 0,
      "columnPosition": 0,
      "id": 0,
      "worldId": 94
    },
    {
      "rowPosition": 0,
      "columnPosition": 1,
      "id": 1,
      "worldId": 94
    },
    {
      "rowPosition": 0,
      "columnPosition": 2,
      "id": 2,
      "worldId": 94
    },
    {
      "rowPosition": 0,
      "columnPosition": 3,
      "id": 3,
      "worldId": 94
    },
    {
      "rowPosition": 0,
      "columnPosition": 4,
      "id": 4,
      "worldId": 94
    },
    {
      "rowPosition": 0,
      "columnPosition": 5,
      "id": 5,
      "worldId": 94
    },
    {
      "rowPosition": 1,
      "columnPosition": 0,
      "id": 6,
      "worldId": 94
    },
    {
      "rowPosition": 1,
      "columnPosition": 1,
      "id": 7,
      "worldId": 94
    },
    {
      "rowPosition": 1,
      "columnPosition": 2,
      "id": 8,
      "worldId": 94
    },
    {
      "rowPosition": 1,
      "columnPosition": 3,
      "id": 9,
      "worldId": 94
    },
    {
      "rowPosition": 1,
      "columnPosition": 4,
      "id": 10,
      "worldId": 94
    },
    {
      "rowPosition": 1,
      "columnPosition": 5,
      "id": 11,
      "worldId": 94
    },
    {
      "rowPosition": 2,
      "columnPosition": 0,
      "id": 12,
      "worldId": 94
    },
    {
      "rowPosition": 2,
      "columnPosition": 1,
      "id": 13,
      "worldId": 94
    },
    {
      "rowPosition": 2,
      "columnPosition": 2,
      "id": 14,
      "worldId": 94
    },
    {
      "rowPosition": 2,
      "columnPosition": 3,
      "id": 15,
      "worldId": 94
    },
    {
      "rowPosition": 2,
      "columnPosition": 4,
      "id": 16,
      "worldId": 94
    },
    {
      "rowPosition": 2,
      "columnPosition": 5,
      "id": 17,
      "worldId": 94
    }
  ],
  "values": {
    "0": 4.0018329023902570185100557864643633365631103515625,
    "1": 3.14441765693920416424589348025619983673095703125,
    "2": 6.5036253761014659602324172738008201122283935546875,
    "3": 7.281234040471499469049376784823834896087646484375,
    "4": 6.69604535420609625617771598626859486103057861328125,
    "5": 6.6985052530772151158089400269091129302978515625,
    "6": 8.371491522851190580922775552608072757720947265625,
    "7": 4.58548885992087207341683097183704376220703125,
    "8": 6.41667750244597101527688209898769855499267578125,
    "9": 3.05279462682828306441251697833649814128875732421875,
    "10": 8.25888453337204708759600180201232433319091796875,
    "11": 8.227112234078649777302416623570024967193603515625,
    "12": 6.676797367564820007146408897824585437774658203125,
    "13": 8.2740009734190973489376119687221944332122802734375,
    "14": 6.711432202417629611090887919999659061431884765625,
    "15": 3.47619842322390315558777729165740311145782470703125,
    "16": 6.347895696769011664173376630060374736785888671875,
    "17": 7.893701157134568546780428732745349407196044921875
  },
  "setupType": "National Bidder Setup",
  "population": 0,
  "id": 0,
  "worldId": 94,
  "setup": {
    "valueInterval": {
      "minValue": 3.0,
      "maxValue": 9.0
    },
    "proximitySize": -1,
    "a": 320,
    "b": 10,
    "setupName": "National Bidder Setup",
    "numberOfBidders": 1
  },
  "implementation": "org.spectrumauctions.sats.core.model.lsvm.LSVMBidder"
}