{
  "LSVM_A": 320,
  "LSVM_B": 10,
  "proximity": [
    {
      "rowPosition": 0,
      "columnPosition": 0,
      "id": 0,
      "worldId": 55
    },
    {
      "rowPosition": 0,
      "columnPosition": 1,
      "id": 1,
      "worldId": 55
    },
    {
      "rowPosition": 0,
      "columnPosition": 2,
      "id": 2,
      "worldId": 55
    },
    {
      "rowPosition": 0,
      "columnPosition": 3,
      "id": 3,
      "worldId": 55
    },
    {
      "rowPosition": 0,
      "columnPosition": 4,
      "id": 4,
      "worldId": 55
    },
    {
      "rowPosition": 0,
      "columnPosition": 5,
      "id": 5,
      "worldId": 55
    },
    {
      "rowPosition": 1,
      "columnPosition": 0,
      "id": 6,
      "worldId": 55
    },
    {
      "rowPosition": 1,
      "columnPosition": 1,
      "id": 7,
      "worldId": 55
    },
    {
      "rowPosition": 1,
      "columnPosition": 2,
      "id": 8,
      "worldId": 55
    },
    {
      "rowPosition": 1,
      "columnPosition": 3,
      "id": 9,
      "worldId": 55
    },
    {
      "rowPosition": 1,
      "columnPosition": 4,
      "id": 10,
      "worldId": 55
    },
    {
      "rowPosition": 1,
      "columnPosition": 5,
      "id": 11,
      "worldId": 55
    },
    {
      "rowPosition": 2,
      "columnPosition": 0,
      "id": 12,
      "worldId": 55
    },
    {
      "rowPosition": 2,
      "columnPosition": 1,
      "id": 13,
      "worldId": 55
    },
    {
      "rowPosition": 2,
      "columnPosition": 2,
      "id": 14,
      "worldId": 55
    },
    {
      "rowPosition": 2,
      "columnPosition": 3,
      "id": 15,
      "worldId": 55
    },
    {
      "rowPosition": 2,
      "columnPosition": 4,
      "id": 16,
      "worldId": 55
    },
    {
      "rowPosition": 2,
      "columnPosition": 5,
      "id": 17,
      "worldId": 55
    }
  ],
  "values": {
    "0": 8.930136067655809029020019806921482086181640625,
    "1": 4.4628769148922611265106752398423850536346435546875,
    "2": 8.739274965692874985734306392259895801544189453125,
    "3": 5.601312416830484863794481498189270496368408203125,
    "4": 4.4212188298035552946885218261741101741790771484375,
    "5": 3.124991812448314476569066755473613739013671875,
    "6": 4.7654584894244873538582396577112376689910888671875,
    "7": 3.968608994174922077746714421664364635944366455078125,
    "8": 6.75822518602722066560772873344831168651580810546875,
    "9": 6.21195296995012480323339332244358956813812255859375,
    "10": 8.47546868282110921200001030229032039642333984375,
    "11": 7.35299909653577454804462831816636025905609130859375,
    "12": 4.14070047330965440579575442825444042682647705078125,
    "13": 4.7637740946955826615294427028857171535491943359375,
    "14": 3.587512593905627600321395220817066729068756103515625,
    "15": 6.41372296250351947577428290969692170619964599609375,
    "16": 4.9262602844161289539215431432239711284637451171875,
    "17": 7.50517267481534755546590531594119966030120849609375
  },
  "setupType": "National Bidder Setup",
  "population": 0,
  "id": 0,
  "worldId": 55,
  "setup": {
    "valueInterval": {
      "minValue": 3.0,
      "maxValue": 9.0
    },
    "proximitySize": -1,
    "a": 320,
    "b": 10,
    "setupName": "National Bidder Setup",
    "numberOfBidders": 1
  },
  "implementation": "org.spectrumauctions.sats.core.model.lsvm.LSVMBidder"
}