{
  "LSVM_A": 320,
  "LSVM_B": 10,
  "proximity": [
    {
      "rowPosition": 0,
      "columnPosition": 0,
      "id": 0,
      "worldId": 40
    },
    {
      "rowPosition": 0,
      "columnPosition": 1,
      "id": 1,
      "worldId": 40
    },
    {
      "rowPosition": 0,
      "columnPosition": 2,
      "id": 2,
      "worldId": 40
    },
    {
      "rowPosition": 0,
      "columnPosition": 3,
      "id": 3,
      "worldId": 40
    },
    {
      "rowPosition": 0,
      "columnPosition": 4,
      "id": 4,
      "worldId": 40
    },
    {
      "rowPosition": 0,
      "columnPosition": 5,
      "id": 5,
      "worldId": 40
    },
    {
      "rowPosition": 1,
      "columnPosition": 0,
      "id": 6,
      "worldId": 40
    },
    {
      "rowPosition": 1,
      "columnPosition": 1,
      "id": 7,
      "worldId": 40
    },
    {
      "rowPosition": 1,
      "columnPosition": 2,
      "id": 8,
      "worldId": 40
    },
    {
      "rowPosition": 1,
      "columnPosition": 3,
      "id": 9,
      "worldId": 40
    },
    {
      "rowPosition": 1,
      "columnPosition": 4,
      "id": 10,
      "worldId": 40
    },
    {
      "rowPosition": 1,
      "columnPosition": 5,
      "id": 11,
      "worldId": 40
    },
    {
      "rowPosition": 2,
      "columnPosition": 0,
      "id": 12,
      "worldId": 40
    },
    {
      "rowPosition": 2,
      "columnPosition": 1,
      "id": 13,
      "worldId": 40
    },
    {
      "rowPosition": 2,
      "columnPosition": 2,
      "id": 14,
      "worldId": 40
    },
    {
      "rowPosition": 2,
      "columnPosition": 3,
      "id": 15,
      "worldId": 40
    },
    {
      "rowPosition": 2,
      "columnPosition": 4,
      "id": 16,
      "worldId": 40
    },
    {
      "rowPosition": 2,
      "columnPosition": 5,
      "id": 17,
      "worldId": 40
    }
  ],
  "values": {
    "0": 7.88394775001478276266198008670471608638763427734375,
    "1": 8.90102524992521892954755458049476146697998046875,
    "2": 6.208590377405183602377292118035256862640380859375,
    "3": 3.543170841669631698778175632469356060028076171875,
    "4": 4.744595520613874128912357264198362827301025390625,
    "5": 5.84875077372942175912839957163669168949127197265625,
    "6": 3.504224688761291783833939916803501546382904052734375,
    "7": 5.016912469608602265225272276438772678375244140625,
    "8": 3.150240684023267068170071070198900997638702392578125,
    "9": 7.4446946563117126771658149664290249347686767578125,
    "10": 8.169120642806550591785708093084394931793212890625,
    "11": 6.32907474439154871248547351569868624210357666015625,
    "12": 6.09507324520057380823345738463103771209716796875,
    "13": 5.4731929094001952051939952070824801921844482421875,
    "14": 6.1810992752381554993235113215632736682891845703125,
    "15": 3.27570921846823015499694520258344709873199462890625,
    "16": 8.4290743335424878068806719966232776641845703125,
    "17": 8.327855946649176388518753810785710811614990234375
  },
  "setupType": "National Bidder Setup",
  "population": 0,
  "id": 0,
  "worldId": 40,
  "setup": {
    "valueInterval": {
      "minValue": 3.0,
      "maxValue": 9.0
    },
    "proximitySize": -1,
    "a": 320,
    "b": 10,
    "setupName": "National Bidder Setup",
    "numberOfBidders": 1
  },
  "implementation": "org.spectrumauctions.sats.core.model.lsvm.LSVMBidder"
}