{
  "LSVM_A": 320,
  "LSVM_B": 10,
  "proximity": [
    {
      "rowPosition": 0,
      "columnPosition": 0,
      "id": 0,
      "worldId": 16
    },
    {
      "rowPosition": 0,
      "columnPosition": 1,
      "id": 1,
      "worldId": 16
    },
    {
      "rowPosition": 0,
      "columnPosition": 2,
      "id": 2,
      "worldId": 16
    },
    {
      "rowPosition": 0,
      "columnPosition": 3,
      "id": 3,
      "worldId": 16
    },
    {
      "rowPosition": 0,
      "columnPosition": 4,
      "id": 4,
      "worldId": 16
    },
    {
      "rowPosition": 0,
      "columnPosition": 5,
      "id": 5,
      "worldId": 16
    },
    {
      "rowPosition": 1,
      "columnPosition": 0,
      "id": 6,
      "worldId": 16
    },
    {
      "rowPosition": 1,
      "columnPosition": 1,
      "id": 7,
      "worldId": 16
    },
    {
      "rowPosition": 1,
      "columnPosition": 2,
      "id": 8,
      "worldId": 16
    },
    {
      "rowPosition": 1,
      "columnPosition": 3,
      "id": 9,
      "worldId": 16
    },
    {
      "rowPosition": 1,
      "columnPosition": 4,
      "id": 10,
      "worldId": 16
    },
    {
      "rowPosition": 1,
      "columnPosition": 5,
      "id": 11,
      "worldId": 16
    },
    {
      "rowPosition": 2,
      "columnPosition": 0,
      "id": 12,
      "worldId": 16
    },
    {
      "rowPosition": 2,
      "columnPosition": 1,
      "id": 13,
      "worldId": 16
    },
    {
      "rowPosition": 2,
      "columnPosition": 2,
      "id": 14,
      "worldId": 16
    },
    {
      "rowPosition": 2,
      "columnPosition": 3,
      "id": 15,
      "worldId": 16
    },
    {
      "rowPosition": 2,
      "columnPosition": 4,
      "id": 16,
      "worldId": 16
    },
    {
      "rowPosition": 2,
      "columnPosition": 5,
      "id": 17,
      "worldId": 16
    }
  ],
  "values": {
    "0": 5.2281647024431361359120273846201598644256591796875,
    "1": 6.797771312762304063426199718378484249114990234375,
    "2": 3.20496610491213917981667691492475569248199462890625,
    "3": 8.084203800709016007886020815931260585784912109375,
    "4": 4.7184789726378308927223770297132432460784912109375,
    "5": 4.7497061020626123450938393943943083286285400390625,
    "6": 5.91703718013219681637337998836301267147064208984375,
    "7": 3.10061896449208784787288095685653388500213623046875,
    "8": 8.966935578693181696507963351905345916748046875,
    "9": 3.01526175600570578438919255859218537807464599609375,
    "10": 6.6450348662743810024267077096737921237945556640625,
    "11": 5.7253143807863242642497425549663603305816650390625,
    "12": 4.990231684125429723053457564674317836761474609375,
    "13": 3.2824910349659486286100218421779572963714599609375,
    "14": 6.569271706345030992224565125070512294769287109375,
    "15": 5.06598331449111327628997969441115856170654296875,
    "16": 5.710355321487877944264255347661674022674560546875,
    "17": 5.26555558700078396583421636023558676242828369140625
  },
  "setupType": "National Bidder Setup",
  "population": 0,
  "id": 0,
  "worldId": 16,
  "setup": {
    "valueInterval": {
      "minValue": 3.0,
      "maxValue": 9.0
    },
    "proximitySize": -1,
    "a": 320,
    "b": 10,
    "setupName": "National Bidder Setup",
    "numberOfBidders": 1
  },
  "implementation": "org.spectrumauctions.sats.core.model.lsvm.LSVMBidder"
}