{
  "LSVM_A": 320,
  "LSVM_B": 10,
  "proximity": [
    {
      "rowPosition": 0,
      "columnPosition": 0,
      "id": 0,
      "worldId": 37
    },
    {
      "rowPosition": 0,
      "columnPosition": 1,
      "id": 1,
      "worldId": 37
    },
    {
      "rowPosition": 0,
      "columnPosition": 2,
      "id": 2,
      "worldId": 37
    },
    {
      "rowPosition": 0,
      "columnPosition": 3,
      "id": 3,
      "worldId": 37
    },
    {
      "rowPosition": 0,
      "columnPosition": 4,
      "id": 4,
      "worldId": 37
    },
    {
      "rowPosition": 0,
      "columnPosition": 5,
      "id": 5,
      "worldId": 37
    },
    {
      "rowPosition": 1,
      "columnPosition": 0,
      "id": 6,
      "worldId": 37
    },
    {
      "rowPosition": 1,
      "columnPosition": 1,
      "id": 7,
      "worldId": 37
    },
    {
      "rowPosition": 1,
      "columnPosition": 2,
      "id": 8,
      "worldId": 37
    },
    {
      "rowPosition": 1,
      "columnPosition": 3,
      "id": 9,
      "worldId": 37
    },
    {
      "rowPosition": 1,
      "columnPosition": 4,
      "id": 10,
      "worldId": 37
    },
    {
      "rowPosition": 1,
      "columnPosition": 5,
      "id": 11,
      "worldId": 37
    },
    {
      "rowPosition": 2,
      "columnPosition": 0,
      "id": 12,
      "worldId": 37
    },
    {
      "rowPosition": 2,
      "columnPosition": 1,
      "id": 13,
      "worldId": 37
    },
    {
      "rowPosition": 2,
      "columnPosition": 2,
      "id": 14,
      "worldId": 37
    },
    {
      "rowPosition": 2,
      "columnPosition": 3,
      "id": 15,
      "worldId": 37
    },
    {
      "rowPosition": 2,
      "columnPosition": 4,
      "id": 16,
      "worldId": 37
    },
    {
      "rowPosition": 2,
      "columnPosition": 5,
      "id": 17,
      "worldId": 37
    }
  ],
  "values": {
    "0": 4.87309213209982505787820628029294312000274658203125,
    "1": 4.1357536459112029803009136230684816837310791015625,
    "2": 5.7150114438898214075379655696451663970947265625,
    "3": 8.986556019513574966595115256495773792266845703125,
    "4": 6.35970769849443939847333240322768688201904296875,
    "5": 6.5092435205860557090318252448923885822296142578125,
    "6": 5.87704286538099207604091134271584451198577880859375,
    "7": 7.455178862177287868462371989153325557708740234375,
    "8": 5.7827546179487701039079183829016983509063720703125,
    "9": 3.992560099376512017244067465071566402912139892578125,
    "10": 4.11826414203908885980354170897044241428375244140625,
    "11": 6.60020945566524375180961214937269687652587890625,
    "12": 5.13630155637653107447704314836300909519195556640625,
    "13": 4.78011236534216532589880443993024528026580810546875,
    "14": 6.76744889116486803004590910859405994415283203125,
    "15": 7.2247219325554627999963486217893660068511962890625,
    "16": 6.851221455668426330021247849799692630767822265625,
    "17": 5.79439961894607424852665644721128046512603759765625
  },
  "setupType": "National Bidder Setup",
  "population": 0,
  "id": 0,
  "worldId": 37,
  "setup": {
    "valueInterval": {
      "minValue": 3.0,
      "maxValue": 9.0
    },
    "proximitySize": -1,
    "a": 320,
    "b": 10,
    "setupName": "National Bidder Setup",
    "numberOfBidders": 1
  },
  "implementation": "org.spectrumauctions.sats.core.model.lsvm.LSVMBidder"
}