{
  "LSVM_A": 160,
  "LSVM_B": 4,
  "proximity": [
    {
      "rowPosition": 1,
      "columnPosition": 5,
      "id": 11,
      "worldId": 14
    },
    {
      "rowPosition": 1,
      "columnPosition": 4,
      "id": 10,
      "worldId": 14
    },
    {
      "rowPosition": 0,
      "columnPosition": 5,
      "id": 5,
      "worldId": 14
    },
    {
      "rowPosition": 2,
      "columnPosition": 5,
      "id": 17,
      "worldId": 14
    },
    {
      "rowPosition": 2,
      "columnPosition": 3,
      "id": 15,
      "worldId": 14
    },
    {
      "rowPosition": 2,
      "columnPosition": 4,
      "id": 16,
      "worldId": 14
    }
  ],
  "values": {
    "16": 11.8850802429397983672743066563270986080169677734375,
    "17": 9.3988995925384006824288007919676601886749267578125,
    "5": 16.185961701527009637402443331666290760040283203125,
    "10": 3.971828723974677899377638823352754116058349609375,
    "11": 13.1172283923126773430567482137121260166168212890625,
    "15": 4.6220479250407375815257182694040238857269287109375
  },
  "setupType": "Regional Bidder Setup",
  "population": 0,
  "id": 1,
  "worldId": 14,
  "setup": {
    "valueInterval": {
      "minValue": 3.0,
      "maxValue": 20.0
    },
    "proximitySize": 2,
    "a": 160,
    "b": 4,
    "setupName": "Regional Bidder Setup",
    "numberOfBidders": 5
  },
  "implementation": "org.spectrumauctions.sats.core.model.lsvm.LSVMBidder"
}